ape_alchemy/__init__.py
ape_alchemy/_utils.py
ape_alchemy/config.py
ape_alchemy/exceptions.py
ape_alchemy/provider.py
ape_alchemy/py.typed
ape_alchemy/trace.py
ape_alchemy/version.py
ape_alchemy-0.8.10.dist-info/licenses/LICENSE
ape_alchemy-0.8.10.dist-info/METADATA
ape_alchemy-0.8.10.dist-info/WHEEL
ape_alchemy-0.8.10.dist-info/top_level.txt
ape_alchemy-0.8.10.dist-info/RECORD
